Metadata-Version: 2.2
Name: persian-editor
Version: 1.0.0
Summary: ویرایشگر متنی فارسی پیشرفته برای جنگو با امکانات کامل از جمله آپلود تصویر، حالت HTML، تمام صفحه و Autosave
Home-page: https://github.com/SaEeD802/persian-editor
Author: Mohammad_Ramezaniyan
Author-email: pltmohammad7@gmail.com
Classifier: Development Status :: 5 - Production/Stable
Classifier: Framework :: Django
Classifier: Programming Language :: Python :: 3
Classifier: License :: OSI Approved :: MIT License
Classifier: Operating System :: OS Independent
License-File: LICENSE
Requires-Dist: Django>=2.2
Requires-Dist: bleach>=3.1.0
Dynamic: author
Dynamic: author-email
Dynamic: classifier
Dynamic: description
Dynamic: description-content-type
Dynamic: home-page
Dynamic: requires-dist
Dynamic: summary
